drf_transaction/__init__.py
drf_transaction/admin.py
drf_transaction/apps.py
drf_transaction/filters.py
drf_transaction/models.py
drf_transaction/serializers.py
drf_transaction/tests.py
drf_transaction/urls.py
drf_transaction/views.py
drf_transaction/migrations/0001_initial.py
drf_transaction/migrations/__init__.py
drf_transaction-0.0.3.dist-info/METADATA
drf_transaction-0.0.3.dist-info/RECORD
drf_transaction-0.0.3.dist-info/WHEEL
drf_transaction-0.0.3.dist-info/top_level.txt
